{"data":[
    {
        "indexid":5841,
        "wordid":2116,
        "word":"\u064a\u064e\u0639\u0652\u0644\u064e\u0645\u064f\u0648\u0646\u064e",
        "rootid":904,
        "rootword":"\u0639 \u0644 \u0645",
        "meanings":"to mark\/sign\/distinguish, creations\/beings, world, science\/learning\/knowledge\/information, aware\/know. By means of which one knows a thing, hence it signifies world or creation, because by it the Creator is known. alim (pl. ulama) - one who is learned\/wise or knows.",
        "sentence":"The word \u064a\u064e\u0639\u0652\u0644\u064e\u0645\u064f\u0648\u0646\u064e comes from the root \u0639 \u0644 \u0645 and is associated with the meanings: to mark\/sign\/distinguish, creations\/beings, world, science\/learning\/knowledge\/information, aware\/know. By means of which one knows a thing, hence it signifies world or creation, because by it the Creator is known. alim (pl. ulama) - one who is learned\/wise or knows."
    },

    {
        "indexid":5841,
        "wordid":2143,
        "word":"\u0645\u064e\u0627",
        "rootid":615,
        "rootword":"\u0645 \u0627",
        "meanings":"",
        "sentence":"The word \u0645\u064e\u0627 comes from the root \u0645 \u0627 and is associated with the meanings: "
    },

    {
        "indexid":5841,
        "wordid":11686,
        "word":"\u062a\u064e\u0641\u0652\u0639\u064e\u0644\u064f\u0648\u0646\u064e",
        "rootid":672,
        "rootword":"\u0641 \u0639 \u0644",
        "meanings":"to do something, He did it, the suffering or receiving the effect of an act, to commit, a doing, to do a deed, a custom\/habit\/manner\/wont.",
        "sentence":"The word \u062a\u064e\u0641\u0652\u0639\u064e\u0644\u064f\u0648\u0646\u064e comes from the root \u0641 \u0639 \u0644 and is associated with the meanings: to do something, He did it, the suffering or receiving the effect of an act, to commit, a doing, to do a deed, a custom\/habit\/manner\/wont."
    }]}