{"data":[
    {
        "indexid":1928,
        "wordid":2214,
        "word":"\u0643\u064f\u0646\u0652\u062a\u064f\u0645\u0652",
        "rootid":369,
        "rootword":"\u0643 \u0648 \u0646",
        "meanings":"(Kaf-Alif-Nun) To be, exist, happen, occur, take place, become, be such or so.",
        "sentence":"The word \u0643\u064f\u0646\u0652\u062a\u064f\u0645\u0652 comes from the root \u0643 \u0648 \u0646 and is associated with the meanings: (Kaf-Alif-Nun) To be, exist, happen, occur, take place, become, be such or so."
    },

    {
        "indexid":1928,
        "wordid":2307,
        "word":"\u0642\u064e\u0627\u0644\u064e",
        "rootid":1568,
        "rootword":"\u0642 \u0648 \u0644",
        "meanings":"to say\/speak, to call, to be named, word\/speech, utterance, a thing said, greeting, discourse, one who says\/speaks. To inspire\/transmit\/relate\/answer\/think\/profess, emit an opinion on, indicate a state or condition or circumstance. qa'ilun - speaker, indicator.",
        "sentence":"The word \u0642\u064e\u0627\u0644\u064e comes from the root \u0642 \u0648 \u0644 and is associated with the meanings: to say\/speak, to call, to be named, word\/speech, utterance, a thing said, greeting, discourse, one who says\/speaks. To inspire\/transmit\/relate\/answer\/think\/profess, emit an opinion on, indicate a state or condition or circumstance. qa'ilun - speaker, indicator."
    },

    {
        "indexid":1928,
        "wordid":2361,
        "word":"\u0627\u0644\u0652\u0643\u064e\u0627\u0641\u0650\u0631\u0650\u064a\u0646\u064e",
        "rootid":1515,
        "rootword":"\u0643 \u0641 \u0631",
        "meanings":"to conceal, to cover, to reject, to disbelieve, to be thankless, unthankful, ungrateful, to disown, deny, faithless, black horse, dark night, tiller\/farmer. [[Perhaps it should be noted that its primary meaning is to cover\/conceal (hence farmer), with active\/conscious intent. From this, is born: to reject\/disbelieve because this is a conscious decision made by a person. Please note one can only reject something after hearing\/seeing\/experiencing it, not before.]]",
        "sentence":"The word \u0627\u0644\u0652\u0643\u064e\u0627\u0641\u0650\u0631\u0650\u064a\u0646\u064e comes from the root \u0643 \u0641 \u0631 and is associated with the meanings: to conceal, to cover, to reject, to disbelieve, to be thankless, unthankful, ungrateful, to disown, deny, faithless, black horse, dark night, tiller\/farmer. [[Perhaps it should be noted that its primary meaning is to cover\/conceal (hence farmer), with active\/conscious intent. From this, is born: to reject\/disbelieve because this is a conscious decision made by a person. Please note one can only reject something after hearing\/seeing\/experiencing it, not before.]]"
    },

    {
        "indexid":1928,
        "wordid":2820,
        "word":"\u0627\u0644\u0652\u0642\u0650\u064a\u064e\u0627\u0645\u064e\u0629\u0650",
        "rootid":850,
        "rootword":"\u0642 \u0648 \u0645",
        "meanings":"stand still or firm, rose\/stand up, managed\/conducted\/ordered\/regulated\/superintended, established, made it straight\/right, maintain\/erect\/observe\/perform, set up, people\/community\/company, abode, stature\/dignity\/rank. aqama - to keep a thing or an affair in a right state.",
        "sentence":"The word \u0627\u0644\u0652\u0642\u0650\u064a\u064e\u0627\u0645\u064e\u0629\u0650 comes from the root \u0642 \u0648 \u0645 and is associated with the meanings: stand still or firm, rose\/stand up, managed\/conducted\/ordered\/regulated\/superintended, established, made it straight\/right, maintain\/erect\/observe\/perform, set up, people\/community\/company, abode, stature\/dignity\/rank. aqama - to keep a thing or an affair in a right state."
    },

    {
        "indexid":1928,
        "wordid":2936,
        "word":"\u0623\u064f\u0648\u062a\u064f\u0648\u0627",
        "rootid":626,
        "rootword":"\u0627 \u062a \u064a",
        "meanings":"to come, to bring, come to pass, come upon, do, commit, arrive, pursue, put forth, show, increase, produce, pay, reach, happen, overtake, draw near, go, hit, meet, join, be engaged or occupied, perpetrate (e.g. crime), undertake",
        "sentence":"The word \u0623\u064f\u0648\u062a\u064f\u0648\u0627 comes from the root \u0627 \u062a \u064a and is associated with the meanings: to come, to bring, come to pass, come upon, do, commit, arrive, pursue, put forth, show, increase, produce, pay, reach, happen, overtake, draw near, go, hit, meet, join, be engaged or occupied, perpetrate (e.g. crime), undertake"
    },

    {
        "indexid":1928,
        "wordid":3052,
        "word":"\u064a\u064e\u0648\u0652\u0645\u064e",
        "rootid":1376,
        "rootword":"\u064a \u0648 \u0645",
        "meanings":"day, era, time, today, this\/that day, age\/period of time.",
        "sentence":"The word \u064a\u064e\u0648\u0652\u0645\u064e comes from the root \u064a \u0648 \u0645 and is associated with the meanings: day, era, time, today, this\/that day, age\/period of time."
    },

    {
        "indexid":1928,
        "wordid":3173,
        "word":"\u0641\u0650\u064a\u0647\u0650\u0645\u0652",
        "rootid":1299,
        "rootword":"\u0641 \u064a",
        "meanings":"Proposition which points to cause, space or time. In, into, amongst, in company with, during, with, of, for, for the sake of, upon, concerning, after, in comparison, about, among, on account of, respecting, by the side of, on, by, against, according to, in respect of.",
        "sentence":"The word \u0641\u0650\u064a\u0647\u0650\u0645\u0652 comes from the root \u0641 \u064a and is associated with the meanings: Proposition which points to cause, space or time. In, into, amongst, in company with, during, with, of, for, for the sake of, upon, concerning, after, in comparison, about, among, on account of, respecting, by the side of, on, by, against, according to, in respect of."
    },

    {
        "indexid":1928,
        "wordid":3318,
        "word":"\u0623\u064e\u064a\u0652\u0646\u064e",
        "rootid":1460,
        "rootword":"\u0627 \u064a \u0646",
        "meanings":"",
        "sentence":"The word \u0623\u064e\u064a\u0652\u0646\u064e comes from the root \u0627 \u064a \u0646 and is associated with the meanings: "
    },

    {
        "indexid":1928,
        "wordid":4176,
        "word":"\u0627\u0644\u0652\u064a\u064e\u0648\u0652\u0645\u064e",
        "rootid":1376,
        "rootword":"\u064a \u0648 \u0645",
        "meanings":"day, era, time, today, this\/that day, age\/period of time.",
        "sentence":"The word \u0627\u0644\u0652\u064a\u064e\u0648\u0652\u0645\u064e comes from the root \u064a \u0648 \u0645 and is associated with the meanings: day, era, time, today, this\/that day, age\/period of time."
    },

    {
        "indexid":1928,
        "wordid":6879,
        "word":"\u0648\u064e\u064a\u064e\u0642\u064f\u0648\u0644\u064f",
        "rootid":1568,
        "rootword":"\u0642 \u0648 \u0644",
        "meanings":"to say\/speak, to call, to be named, word\/speech, utterance, a thing said, greeting, discourse, one who says\/speaks. To inspire\/transmit\/relate\/answer\/think\/profess, emit an opinion on, indicate a state or condition or circumstance. qa'ilun - speaker, indicator.",
        "sentence":"The word \u0648\u064e\u064a\u064e\u0642\u064f\u0648\u0644\u064f comes from the root \u0642 \u0648 \u0644 and is associated with the meanings: to say\/speak, to call, to be named, word\/speech, utterance, a thing said, greeting, discourse, one who says\/speaks. To inspire\/transmit\/relate\/answer\/think\/profess, emit an opinion on, indicate a state or condition or circumstance. qa'ilun - speaker, indicator."
    },

    {
        "indexid":1928,
        "wordid":11515,
        "word":"\u064a\u064f\u062e\u0652\u0632\u0650\u064a\u0647\u0650\u0645\u0652",
        "rootid":107,
        "rootword":"\u062e \u0632 \u064a",
        "meanings":"To be or become abased\/vile\/despicable\/abject, fall into trial or affliction and evil, manifest foul actions or qualities, to be confounded or perplexed by reason of disgrace, moved or affected with shame.",
        "sentence":"The word \u064a\u064f\u062e\u0652\u0632\u0650\u064a\u0647\u0650\u0645\u0652 comes from the root \u062e \u0632 \u064a and is associated with the meanings: To be or become abased\/vile\/despicable\/abject, fall into trial or affliction and evil, manifest foul actions or qualities, to be confounded or perplexed by reason of disgrace, moved or affected with shame."
    },

    {
        "indexid":1928,
        "wordid":11516,
        "word":"\u0634\u064f\u0631\u064e\u0643\u064e\u0627\u0621\u0650\u064a\u064e",
        "rootid":566,
        "rootword":"\u0634 \u0631 \u0643",
        "meanings":"to be a companion, be sharer\/partner. shirkun - share, participation, polytheism, idolatry, making associate\/partner with Allah. shariik (pl. shurakaa) - associate, partner, sharer. Nouns of the second declension when followed by the affixed pronouns take the three inflexions thus shurakaa, shurakaa'i, shurakaa'a. shaarak (vb. 3) - to share with. ashraka (vb. 4) - to make a sharer or associate, give companions (e.g. to God), be a polytheist or idolater. ashraktumuuni - you associated me as partner. mushrik - one who gives associate to God, polytheist. mushtarikun (vb. 8) - one who partakes or shares. ",
        "sentence":"The word \u0634\u064f\u0631\u064e\u0643\u064e\u0627\u0621\u0650\u064a\u064e comes from the root \u0634 \u0631 \u0643 and is associated with the meanings: to be a companion, be sharer\/partner. shirkun - share, participation, polytheism, idolatry, making associate\/partner with Allah. shariik (pl. shurakaa) - associate, partner, sharer. Nouns of the second declension when followed by the affixed pronouns take the three inflexions thus shurakaa, shurakaa'i, shurakaa'a. shaarak (vb. 3) - to share with. ashraka (vb. 4) - to make a sharer or associate, give companions (e.g. to God), be a polytheist or idolater. ashraktumuuni - you associated me as partner. mushrik - one who gives associate to God, polytheist. mushtarikun (vb. 8) - one who partakes or shares. "
    },

    {
        "indexid":1928,
        "wordid":11517,
        "word":"\u062a\u064f\u0634\u064e\u0627\u0642\u0651\u064f\u0648\u0646\u064e",
        "rootid":1455,
        "rootword":"\u0634 \u0642 \u0642",
        "meanings":"pass along the way, cross, open a way\/passage\/vent\/channel, cut\/split\/divided\/clave\/ripped\/tore.",
        "sentence":"The word \u062a\u064f\u0634\u064e\u0627\u0642\u0651\u064f\u0648\u0646\u064e comes from the root \u0634 \u0642 \u0642 and is associated with the meanings: pass along the way, cross, open a way\/passage\/vent\/channel, cut\/split\/divided\/clave\/ripped\/tore."
    },

    {
        "indexid":1928,
        "wordid":11518,
        "word":"\u0627\u0644\u0652\u0639\u0650\u0644\u0652\u0645\u064e",
        "rootid":904,
        "rootword":"\u0639 \u0644 \u0645",
        "meanings":"to mark\/sign\/distinguish, creations\/beings, world, science\/learning\/knowledge\/information, aware\/know. By means of which one knows a thing, hence it signifies world or creation, because by it the Creator is known. alim (pl. ulama) - one who is learned\/wise or knows.",
        "sentence":"The word \u0627\u0644\u0652\u0639\u0650\u0644\u0652\u0645\u064e comes from the root \u0639 \u0644 \u0645 and is associated with the meanings: to mark\/sign\/distinguish, creations\/beings, world, science\/learning\/knowledge\/information, aware\/know. By means of which one knows a thing, hence it signifies world or creation, because by it the Creator is known. alim (pl. ulama) - one who is learned\/wise or knows."
    },

    {
        "indexid":1928,
        "wordid":11519,
        "word":"\u0627\u0644\u0652\u062e\u0650\u0632\u0652\u064a\u064e",
        "rootid":107,
        "rootword":"\u062e \u0632 \u064a",
        "meanings":"To be or become abased\/vile\/despicable\/abject, fall into trial or affliction and evil, manifest foul actions or qualities, to be confounded or perplexed by reason of disgrace, moved or affected with shame.",
        "sentence":"The word \u0627\u0644\u0652\u062e\u0650\u0632\u0652\u064a\u064e comes from the root \u062e \u0632 \u064a and is associated with the meanings: To be or become abased\/vile\/despicable\/abject, fall into trial or affliction and evil, manifest foul actions or qualities, to be confounded or perplexed by reason of disgrace, moved or affected with shame."
    },

    {
        "indexid":1928,
        "wordid":11520,
        "word":"\u0648\u064e\u0627\u0644\u0633\u0651\u064f\u0648\u0621\u064e",
        "rootid":498,
        "rootword":"\u0633 \u0648 \u0627",
        "meanings":"to treat badly, do evil to disgrace, be evil\/wicked\/vicious, ill, anything that makes a person sad and sorrowful, bad action, mischief and corruption, sin, evil doer, wretched or grievous, vex, annoy. su'atun (pl. suat) - corpse, external portion of both sexes, shame.",
        "sentence":"The word \u0648\u064e\u0627\u0644\u0633\u0651\u064f\u0648\u0621\u064e comes from the root \u0633 \u0648 \u0627 and is associated with the meanings: to treat badly, do evil to disgrace, be evil\/wicked\/vicious, ill, anything that makes a person sad and sorrowful, bad action, mischief and corruption, sin, evil doer, wretched or grievous, vex, annoy. su'atun (pl. suat) - corpse, external portion of both sexes, shame."
    }]}